walnutgen/__init__.py
walnutgen/__main__.py
walnutgen/function.py
walnutgen/generator.py
walnutgen-0.0.5.dist-info/LICENSE
walnutgen-0.0.5.dist-info/METADATA
walnutgen-0.0.5.dist-info/WHEEL
walnutgen-0.0.5.dist-info/top_level.txt
walnutgen-0.0.5.dist-info/RECORD
