Metadata-Version: 2.1
Name: walnutgen
Version: 0.0.5
Summary: A dead simple, configurable static site generator
Home-page: UNKNOWN
Author: unsafecast
Author-email: UNKNOWN
License: MIT
Platform: UNKNOWN
